upliftnet/__init__.py
upliftnet/data.py
upliftnet/metrics.py
upliftnet/net.py
upliftnet/plots.py
upliftnet/utils.py
upliftnet-0.0.4.dist-info/METADATA
upliftnet-0.0.4.dist-info/WHEEL
upliftnet-0.0.4.dist-info/licenses/LICENSE
upliftnet-0.0.4.dist-info/RECORD
