Metadata-Version: 2.1
Name: upliftnet
Version: 0.0.4
Summary: Causal loss and metric for neural networks
Project-URL: Homepage, https://github.com/janhelcl/upliftnet
Project-URL: Issues, https://github.com/janhelcl/upliftnet/issues
Author-email: Jan Helcl <janhelcl@gmail.com>
License-File: LICENSE
Classifier: License :: OSI Approved :: MIT License
Classifier: Operating System :: OS Independent
Classifier: Programming Language :: Python :: 3
Requires-Python: >=3.8
Requires-Dist: matplotlib==3.8.2
Requires-Dist: numpy==1.26.2
Requires-Dist: pandas==2.1.3
Requires-Dist: scikit-learn==1.3.2
Requires-Dist: scipy==1.11.4
Requires-Dist: seaborn==0.13.0
Requires-Dist: tensorflow==2.15.0
